flatten_json/__init__.py
flatten_json-0.1.13.dist-info/LICENSE
flatten_json-0.1.13.dist-info/METADATA
flatten_json-0.1.13.dist-info/WHEEL
flatten_json-0.1.13.dist-info/entry_points.txt
flatten_json-0.1.13.dist-info/top_level.txt
flatten_json-0.1.13.dist-info/RECORD
