Metadata-Version: 2.1
Name: flatten_json
Version: 0.1.13
Summary: Flatten JSON objects
Home-page: https://github.com/amirziai/flatten
Author: Amir Ziai
Author-email: arziai@gmail.com
License: MIT
Keywords: json,flatten,pandas
Platform: UNKNOWN
